supplyseer/__init__.py
supplyseer/eoq.py
supplyseer/main.py
supplyseer/bayesian/__init__.py
supplyseer/bayesian/bayesian_eoq.py
supplyseer/experimental/differential calculus/__init__.py
supplyseer/experimental/exotic_supplychain/__init__.py
supplyseer/experimental/exotic_supplychain/api.py
supplyseer/experimental/exotic_supplychain/gdeltmonitor.py
supplyseer/experimental/exotic_supplychain/geo-nb.ipynb
supplyseer/experimental/exotic_supplychain/geopolitical.py
supplyseer/experimental/exotic_supplychain/supplychaingraphs.py
supplyseer/experimental/vector analysis/__init__.py
supplyseer/experimental/vector analysis/inventory-demand-flow-direction.ipynb
supplyseer/gametheory/__init__.py
supplyseer/gametheory/coopgame.py
supplyseer/gametheory/gameconfig.py
supplyseer/models/__init__.py
supplyseer/models/ml/__init__.py
supplyseer/models/ml/bayesiandag.py
supplyseer/models/ml/neuralnets.py
supplyseer/models/statistical/__init__.py
supplyseer/models/statistical/arima.py
supplyseer/models/statistical/pca.py
supplyseer/models/statistical/stochasticprocess.py
supplyseer/models/topological/__init__.py
supplyseer/models/topological/takens.py
supplyseer/optimization/__init__.py
supplyseer/optimization/cpsat.py
supplyseer/sdk-shelfy/__init__.py
supplyseer/sdk-shelfy/system_init.py
supplyseer/sdk-shelfy/config/__init__.py
supplyseer/sdk-shelfy/config/calibration.yml
supplyseer/sdk-shelfy/config/logging_config.yml
supplyseer/sdk-shelfy/config/settings.yml
supplyseer/sdk-shelfy/hardware/__init__.py
supplyseer/sdk-shelfy/hardware/arduino_handler.py
supplyseer/sdk-shelfy/hardware/calibration.py
supplyseer/sdk-shelfy/hardware/sensor_reader.py
supplyseer/sdk-shelfy/processing/__init__.py
supplyseer/sdk-shelfy/processing/data_processor.py
supplyseer/sdk-shelfy/processing/filter.py
supplyseer/sdk-shelfy/processing/matrix_handler.py
supplyseer/sdk-shelfy/utils/__init__.py
supplyseer/sdk-shelfy/utils/config.py
supplyseer/sdk-shelfy/utils/exceptions.py
supplyseer/sdk-shelfy/utils/logger.py
supplyseer-0.2.3.dist-info/METADATA
supplyseer-0.2.3.dist-info/WHEEL
supplyseer-0.2.3.dist-info/licenses/LICENSE
supplyseer-0.2.3.dist-info/RECORD
