Metadata-Version: 2.4
Name: supplyseer
Version: 0.2.3
Summary: SupplySeer is a library for Applied Computational Supply Chain & Logistics. Unlock Neural Nets, Bayesian EOQ, Optimization, Time Series, Game Theory, and more for smarter decisions.
Project-URL: Homepage, https://github.com/jakorostami/supplyseer
Project-URL: Bug Tracker, https://github.com/jakorostami/supplyseer/issues
Author-email: Jako Rostami <rostami.jako@gmail.com>
License-File: LICENSE
Keywords: bayesian-networks,coalition-formation,game-theory,inventory-management,logistics,operations-research,optimization,risk-analysis,supply-chain
Classifier: Development Status :: 3 - Alpha
Classifier: Intended Audience :: Manufacturing
Classifier: Intended Audience :: Science/Research
Classifier: License :: OSI Approved :: GNU Affero General Public License v3
Classifier: Operating System :: OS Independent
Classifier: Programming Language :: Python :: 3
Classifier: Programming Language :: Python :: 3.9
Classifier: Programming Language :: Python :: 3.10
Classifier: Programming Language :: Python :: 3.11
Classifier: Programming Language :: Python :: 3.12
Classifier: Programming Language :: Python :: 3.13
Classifier: Topic :: Office/Business :: Financial :: Accounting
Classifier: Topic :: Office/Business :: Financial :: Investment
Classifier: Topic :: Office/Business :: Scheduling
Classifier: Topic :: Scientific/Engineering :: Artificial Intelligence
Classifier: Topic :: Scientific/Engineering :: Mathematics
Requires-Python: >=3.9
